connpy/__init__.py
connpy/__main__.py
connpy/_version.py
connpy/ai.py
connpy/api.py
connpy/completion.py
connpy/configfile.py
connpy/connapp.py
connpy/core.py
connpy/hooks.py
connpy/plugins.py
connpy/printer.py
connpy/core_plugins/capture.py
connpy/core_plugins/context.py
connpy/core_plugins/sync.py
connpy/core_plugins/sync_client
connpy-4.2.dist-info/licenses/LICENSE
connpy-4.2.dist-info/METADATA
connpy-4.2.dist-info/WHEEL
connpy-4.2.dist-info/entry_points.txt
connpy-4.2.dist-info/top_level.txt
connpy-4.2.dist-info/RECORD
