Metadata-Version: 2.4
Name: connpy
Version: 4.2
Summary: Connpy is a SSH/Telnet connection manager and automation module
Home-page: https://github.com/fluzzi/connpy
Author: Federico Luzzi
Author-email: fluzzi@gmail.com
License: Custom Software License
Project-URL: Bug Tracker, https://github.com/fluzzi/connpy/issues
Project-URL: Documentation, https://fluzzi.github.io/connpy/
Keywords: networking,automation,docker,kubernetes,ssh,telnet,connection manager
Classifier: Development Status :: 4 - Beta
Classifier: Topic :: System :: Networking
Classifier: Intended Audience :: Telecommunications Industry
Classifier: Programming Language :: Python :: 3
Classifier: Natural Language :: English
Classifier: Operating System :: MacOS
Classifier: Operating System :: Unix
License-File: LICENSE
Requires-Dist: inquirer
Requires-Dist: pexpect
Requires-Dist: pycryptodome
Requires-Dist: Flask
Requires-Dist: Flask_Cors
Requires-Dist: pyfzf
Requires-Dist: waitress
Requires-Dist: PyYAML
Requires-Dist: openai
Requires-Dist: rich
Requires-Dist: protobuf
Requires-Dist: google_api_python_client
Requires-Dist: google_auth_oauthlib
Dynamic: license-file
